tutobooks/__init__.py
tutobooks/tutobooks.py
tutobooks-0.1.0.dist-info/LICENSE
tutobooks-0.1.0.dist-info/METADATA
tutobooks-0.1.0.dist-info/WHEEL
tutobooks-0.1.0.dist-info/entry_points.txt
tutobooks-0.1.0.dist-info/top_level.txt
tutobooks-0.1.0.dist-info/RECORD
