Metadata-Version: 2.1
Name: tutobooks
Version: 0.1.0
Summary: A simple package to convert between tutobooks python files, jupyter notebooks and
Home-page: https://github.com/lukewood/tutobooks
Author: Keras team
Author-email: lukewoodcs@gmail.com
License: Apache License 2.0
Platform: UNKNOWN
Classifier: Programming Language :: Python
Classifier: Programming Language :: Python :: 3.7
Classifier: Operating System :: Unix
Classifier: Operating System :: Microsoft :: Windows
Classifier: Operating System :: MacOS
Classifier: Topic :: Scientific/Engineering
Classifier: Topic :: Software Development
License-File: LICENSE
Requires-Dist: packaging
Requires-Dist: absl-py
Provides-Extra: tests
Requires-Dist: flake8 ; extra == 'tests'
Requires-Dist: isort ; extra == 'tests'
Requires-Dist: black ; extra == 'tests'
Requires-Dist: pytest ; extra == 'tests'
